databoomer/__init__.py
databoomer/core.py
databoomer-0.1.1.dist-info/LICENSE
databoomer-0.1.1.dist-info/METADATA
databoomer-0.1.1.dist-info/WHEEL
databoomer-0.1.1.dist-info/top_level.txt
databoomer-0.1.1.dist-info/RECORD
